fate_llm/__init__.py
fate_llm/algo/__init__.py
fate_llm/algo/dp/__init__.py
fate_llm/algo/dp/dp_trainer.py
fate_llm/algo/dp/opacus_compatibility/__init__.py
fate_llm/algo/dp/opacus_compatibility/transformers_compate.py
fate_llm/algo/dp/opacus_compatibility/grad_sample/__init__.py
fate_llm/algo/dp/opacus_compatibility/grad_sample/embedding.py
fate_llm/algo/dp/opacus_compatibility/optimizers/__init__.py
fate_llm/algo/dp/opacus_compatibility/optimizers/optimizer.py
fate_llm/algo/fdkt/__init__.py
fate_llm/algo/fdkt/fdkt_data_aug.py
fate_llm/algo/fdkt/inference_inst.py
fate_llm/algo/fdkt/cluster/__init__.py
fate_llm/algo/fdkt/cluster/cluster.py
fate_llm/algo/fdkt/cluster/cluster_method.py
fate_llm/algo/fdkt/utils/__init__.py
fate_llm/algo/fdkt/utils/dp_loss.py
fate_llm/algo/fdkt/utils/invalid_data_filter.py
fate_llm/algo/fdkt/utils/text_generate.py
fate_llm/algo/fedavg/__init__.py
fate_llm/algo/fedavg/fedavg.py
fate_llm/algo/fedkseed/__init__.py
fate_llm/algo/fedkseed/args.py
fate_llm/algo/fedkseed/fedkseed.py
fate_llm/algo/fedkseed/optimizer.py
fate_llm/algo/fedkseed/pytorch_utils.py
fate_llm/algo/fedkseed/trainer.py
fate_llm/algo/fedkseed/zo_utils.py
fate_llm/algo/fedmkt/__init__.py
fate_llm/algo/fedmkt/fedmkt.py
fate_llm/algo/fedmkt/fedmkt_data_collator.py
fate_llm/algo/fedmkt/fedmkt_trainer.py
fate_llm/algo/fedmkt/token_alignment/__init__.py
fate_llm/algo/fedmkt/token_alignment/spectal_token_mapping.py
fate_llm/algo/fedmkt/token_alignment/token_align.py
fate_llm/algo/fedmkt/token_alignment/vocab_mapping.py
fate_llm/algo/fedmkt/utils/__init__.py
fate_llm/algo/fedmkt/utils/dataset_sync_util.py
fate_llm/algo/fedmkt/utils/generate_logit_utils.py
fate_llm/algo/fedmkt/utils/tokenizer_tool.py
fate_llm/algo/fedmkt/utils/vars_define.py
fate_llm/algo/inferdpt/__init__.py
fate_llm/algo/inferdpt/_encode_decode.py
fate_llm/algo/inferdpt/inferdpt.py
fate_llm/algo/inferdpt/utils.py
fate_llm/algo/offsite_tuning/__init__.py
fate_llm/algo/offsite_tuning/offsite_tuning.py
fate_llm-2.2.0.dist-info/METADATA
fate_llm-2.2.0.dist-info/WHEEL
fate_llm-2.2.0.dist-info/entry_points.txt
fate_llm-2.2.0.dist-info/top_level.txt
fate_llm-2.2.0.dist-info/RECORD
